{"items":[{"category":"Category 1","homepage_url":"https://learn.microsoft.com/en-us/dotnet/csharp/","id":"category-1--subcategory-1-1--c","logo":"logos/5a998aaca3da0ccedfe651fd9835493752cd9388f687b28483e1d61b97ab7155.png","name":"C#","subcategory":"Subcategory 1-1","website":"https://learn.microsoft.com/en-us/dotnet/csharp/","description":"This is the description of item 1","repositories":[{"url":"https://github.com/dotnet/csharplang","primary":true}]},{"category":"Category 1","homepage_url":"https://dev.java/","id":"category-1--subcategory-1-1--java","logo":"logos/8240b523cf5c10bf655974085503753d25acb48e0107f5c60c5a4018123ec241.png","name":"Java","subcategory":"Subcategory 1-1","website":"https://dev.java/","description":"This is the description of item 2","repositories":[{"url":"https://github.com/openjdk/jdk","primary":true}]}]}